jennifer/__init__.py
jennifer/app_pool.ini
jennifer/network_logger.py
jennifer/startup.py
jennifer/util.py
jennifer/admin/__init__.py
jennifer/admin/generate_config.py
jennifer/admin/run.py
jennifer/admin/sitecustomize.py
jennifer/agent/__init__.py
jennifer/agent/active_object.py
jennifer/agent/agent.py
jennifer/agent/app_config.py
jennifer/agent/class_info.py
jennifer/agent/class_selector.py
jennifer/agent/config_parser.py
jennifer/agent/int_bound_set.py
jennifer/agent/profiler.py
jennifer/agent/python_def_visitor.py
jennifer/agent/sortedlist.py
jennifer/agent/sortedset.py
jennifer/agent/test_class_selector.py
jennifer/agent/util.py
jennifer/api/__init__.py
jennifer/api/format.py
jennifer/api/proxy.py
jennifer/api/task.py
jennifer/api/util.py
jennifer/bin/darwin/amd64/jennifer_agent
jennifer/bin/darwin/arm64/jennifer_agent
jennifer/bin/linux/amd64/jennifer_agent
jennifer/bootstrap/__init__.py
jennifer/bootstrap/console_logger.py
jennifer/bootstrap/sitecustomize.py
jennifer/hooks/__init__.py
jennifer/hooks/app_django.py
jennifer/hooks/app_fastapi.py
jennifer/hooks/app_flask.py
jennifer/hooks/app_starlette_async.py
jennifer/hooks/app_uvicorn_async.py
jennifer/hooks/db_cx_oracle.py
jennifer/hooks/db_mysqlclient.py
jennifer/hooks/db_oracledb.py
jennifer/hooks/db_psycopg2.py
jennifer/hooks/db_pymongo.py
jennifer/hooks/db_pymssql.py
jennifer/hooks/db_pymysql.py
jennifer/hooks/db_pyodbc.py
jennifer/hooks/db_redis.py
jennifer/hooks/db_sqlite3.py
jennifer/hooks/external_celery.py
jennifer/hooks/external_requests.py
jennifer/hooks/external_urllib.py
jennifer/hooks/external_urllib2.py
jennifer/hooks/external_urllib3.py
jennifer/hooks/mod_asyncio.py
jennifer/hooks/mod_uvloop.py
jennifer/hooks/util.py
jennifer/pconstants/__init__.py
jennifer/protocol/__init__.py
jennifer/protocol/db_message.py
jennifer/protocol/error.py
jennifer/protocol/external_call.py
jennifer/protocol/file.py
jennifer/protocol/message.py
jennifer/protocol/method.py
jennifer/protocol/profile_data.py
jennifer_python-5.6.4.7.dist-info/METADATA
jennifer_python-5.6.4.7.dist-info/WHEEL
jennifer_python-5.6.4.7.dist-info/entry_points.txt
jennifer_python-5.6.4.7.dist-info/top_level.txt
jennifer_python-5.6.4.7.dist-info/RECORD
