Metadata-Version: 2.1
Name: jennifer-python
Version: 5.6.4.7
Summary: JENNIFER, JenniferSoft APM, python agent.
Home-page: https://jennifersoft.com
Author: JENNIFER
Author-email: app@jennifersoft.com
License: Proprietary
Platform: UNKNOWN
Classifier: Operating System :: MacOS :: MacOS X
Classifier: Operating System :: POSIX :: Linux
Classifier: License :: Other/Proprietary License
